suadoPygameTools/__init__.py
suadoPygameTools-0.0.1.dist-info/LICENSE
suadoPygameTools-0.0.1.dist-info/METADATA
suadoPygameTools-0.0.1.dist-info/WHEEL
suadoPygameTools-0.0.1.dist-info/top_level.txt
suadoPygameTools-0.0.1.dist-info/RECORD
