Metadata-Version: 2.1
Name: suadoPygameTools
Version: 0.0.1
Summary: help creating simple 2d games (with pygame) faster.
Home-page: https://github.com/SuadoCowboy/suadoPygameTools
Author: Suado Cowboy
Author-email: luccacsg@gmail.com
Classifier: Programming Language :: Python :: 3
Classifier: License :: OSI Approved :: MIT License
Classifier: Operating System :: OS Independent
Requires-Python: >=3.9
License-File: LICENSE
